Metadata-Version: 1.1
Name: kotlin-kernel
Version: 0.0.1
Summary: A Kotlin kernel for Jupyter
Home-page: https://github.com/HelgeCPH/kotlin_kernel
Author: HelgeCPH
Author-email: ropf@itu.dk
License: UNKNOWN
Platform: UNKNOWN
Classifier: Development Status :: 3 - Alpha
Classifier: Intended Audience :: Education
Classifier: Intended Audience :: Developers
Classifier: Intended Audience :: Science/Research
Classifier: License :: OSI Approved :: GNU General Public License v3 (GPLv3)
Classifier: Operating System :: MacOS :: MacOS X
Classifier: Operating System :: Microsoft :: Windows
Classifier: Operating System :: POSIX
Classifier: Programming Language :: Python :: 3
